viral_loops_api/__init__.py
viral_loops_api/altruistic_referral.py
viral_loops_api/base.py
viral_loops_api/exceptions.py
viral_loops_api/utils.py
viral_loops_api/utils_mixin.py
viral_loops_api-0.4.0.dist-info/METADATA
viral_loops_api-0.4.0.dist-info/RECORD
viral_loops_api-0.4.0.dist-info/WHEEL
viral_loops_api-0.4.0.dist-info/top_level.txt
