Metadata-Version: 2.1
Name: viral-loops-api
Version: 0.4.0
Summary: A simplistic API client for viral-loops
Home-page: https://github.com/bequest/viral-loops-api
Author: Bequest Inc.
Author-email: oss@willing.com
License: GPLv3
Platform: UNKNOWN
